smdebug_rulesconfig/__init__.py
smdebug_rulesconfig/_version.py
smdebug_rulesconfig/debugger_rules/__init__.py
smdebug_rulesconfig/debugger_rules/_collections.py
smdebug_rulesconfig/debugger_rules/_constants.py
smdebug_rulesconfig/debugger_rules/_ruleGroups.py
smdebug_rulesconfig/debugger_rules/_utils.py
smdebug_rulesconfig/debugger_rules/builtin_rules.py
smdebug_rulesconfig/debugger_rules/rule_config_jsons/collections.json
smdebug_rulesconfig/debugger_rules/rule_config_jsons/ruleConfigs.json
smdebug_rulesconfig/debugger_rules/rule_config_jsons/ruleGroups.json
smdebug_rulesconfig/profiler_rules/__init__.py
smdebug_rulesconfig/profiler_rules/rules.py
smdebug_rulesconfig/profiler_rules/utils.py
smdebug_rulesconfig-1.0.0.dist-info/LICENSE
smdebug_rulesconfig-1.0.0.dist-info/METADATA
smdebug_rulesconfig-1.0.0.dist-info/NOTICE
smdebug_rulesconfig-1.0.0.dist-info/WHEEL
smdebug_rulesconfig-1.0.0.dist-info/top_level.txt
smdebug_rulesconfig-1.0.0.dist-info/RECORD
