Metadata-Version: 2.1
Name: smdebug-rulesconfig
Version: 1.0.0
Summary: SMDebug RulesConfig
Home-page: https://github.com/awslabs/sagemaker-debugger-rulesconfig
Author: AWS DeepLearning Team
License: Apache License Version 2.0
Platform: UNKNOWN
Classifier: Programming Language :: Python :: 3
Classifier: License :: OSI Approved :: Apache Software License
Classifier: Operating System :: OS Independent
Requires-Python: >=2.7
